SanicForPythoneer/README.md
SanicForPythoneer/__init__.py
SanicForPythoneer/__main__.py
SanicForPythoneer/file.epub
SanicForPythoneer/index.html
SanicForPythoneer/css/__init__.py
SanicForPythoneer/css/annotations.css
SanicForPythoneer/css/main.css
SanicForPythoneer/css/normalize.css
SanicForPythoneer/css/popup.css
SanicForPythoneer/font/__init__.py
SanicForPythoneer/font/fontello.eot
SanicForPythoneer/font/fontello.svg
SanicForPythoneer/font/fontello.ttf
SanicForPythoneer/font/fontello.woff
SanicForPythoneer/img/__init__.py
SanicForPythoneer/img/annotator-glyph-sprite.png
SanicForPythoneer/img/annotator-icon-sprite.png
SanicForPythoneer/img/apple-touch-icon.png
SanicForPythoneer/img/cancelfullscreen.png
SanicForPythoneer/img/close.png
SanicForPythoneer/img/fullscreen.png
SanicForPythoneer/img/loader.gif
SanicForPythoneer/img/menu-icon.png
SanicForPythoneer/img/save.png
SanicForPythoneer/img/saved.png
SanicForPythoneer/img/settings-s.png
SanicForPythoneer/img/settings.png
SanicForPythoneer/img/star.png
SanicForPythoneer/js/__init__.py
SanicForPythoneer/js/epub.js
SanicForPythoneer/js/epub.min.js
SanicForPythoneer/js/epub.min.map
SanicForPythoneer/js/hooks.min.js
SanicForPythoneer/js/hooks.min.map
SanicForPythoneer/js/reader.js
SanicForPythoneer/js/reader.js.map
SanicForPythoneer/js/reader.min.js
SanicForPythoneer/js/reader.min.map
SanicForPythoneer/js/hooks/__init__.py
SanicForPythoneer/js/hooks/extensions/__init__.py
SanicForPythoneer/js/hooks/extensions/highlight.js
SanicForPythoneer/js/libs/__init__.py
SanicForPythoneer/js/libs/jquery.min.js
SanicForPythoneer/js/libs/localforage.min.js
SanicForPythoneer/js/libs/screenfull.js
SanicForPythoneer/js/libs/screenfull.min.js
SanicForPythoneer/js/libs/zip.min.js
SanicForPythoneer/js/plugins/__init__.py
SanicForPythoneer/js/plugins/hypothesis.js
SanicForPythoneer/js/plugins/search.js
sanic_for_pythoneer-2024.3.3.0.dist-info/METADATA
sanic_for_pythoneer-2024.3.3.0.dist-info/WHEEL
sanic_for_pythoneer-2024.3.3.0.dist-info/entry_points.txt
sanic_for_pythoneer-2024.3.3.0.dist-info/top_level.txt
sanic_for_pythoneer-2024.3.3.0.dist-info/RECORD
